pypipre/README.md
pypipre/__init__.py
pypipre/__main__.py
pypipre/_pypipre.cpython-310-x86_64-linux-gnu.so
pypipre/_pypipre.cpython-311-x86_64-linux-gnu.so
pypipre/_pypipre.cpython-312-x86_64-linux-gnu.so
pypipre/_pypipre.cpython-38-x86_64-linux-gnu.so
pypipre/_pypipre.cpython-39-x86_64-linux-gnu.so
pypipre/bin/hydra_pmi_proxy
pypipre/bin/mpiexec.hydra
pypipre/examples/solver.json
pypipre/examples/solver.py
pypipre/examples/thermal1.mtx
pypipre/examples/thermal1_b.mtx
pypipre/lib/libmpi.so.12
pypipre/lib/libpipre.so
pypipre/licenses/amgcl-LICENSE.md
pypipre/licenses/glog-LICENSE.md
pypipre-1.0.4.dist-info/METADATA
pypipre-1.0.4.dist-info/WHEEL
pypipre-1.0.4.dist-info/top_level.txt
pypipre-1.0.4.dist-info/RECORD
